{"type":"FeatureCollection","features":[{"geometry":{"coordinates":[[[102.632858,-3.5107590000000015],[102.625713,-3.511090000000001],[102.625142,-3.515787],[102.632956,-3.515446000000001],[102.632858,-3.5107590000000015]]],"geodesic":true,"type":"Polygon"},"id":"20001021034919","properties":{"AOT":0.156,"H2O":4.780000305175781,"O3":0.252,"date":{"type":"Date","value":972100159000},"doy":295.15924768518516,"solar_z":17.742791999999994,"swir":{"swir1":null,"swir2":null,"swir3":null,"swir4":null,"swir5":null,"swir6":null},"tir":{"bkgd_rad":{"tir1":null,"tir2":null,"tir3":null,"tir4":null,"tir5":null},"lake_rad":{"tir1":null,"tir2":null,"tir3":null,"tir4":null,"tir5":null}},"vnir":{"mean_radiance":{"green":null,"nir":null,"red":null},"pixel_counts":{"cloud":1916.0,"lake":0.0,"valid":{"green":1916,"nir":1916,"red":1916}}}},"type":"Feature"},{"geometry":{"coordinates":[[[102.632858,-3.5107590000000015],[102.625713,-3.511090000000001],[102.625142,-3.515787],[102.632956,-3.515446000000001],[102.632858,-3.5107590000000015]]],"geodesic":true,"type":"Polygon"},"id":"20001208034756","properties":{"AOT":0.227,"H2O":4.480000305175781,"O3":0.245,"date":{"type":"Date","value":976247276000},"doy":343.15828703703704,"solar_z":26.245548,"swir":{"swir1":null,"swir2":null,"swir3":null,"swir4":null,"swir5":null,"swir6":null},"tir":{"bkgd_rad":{"tir1":null,"tir2":null,"tir3":null,"tir4":null,"tir5":null},"lake_rad":{"tir1":null,"tir2":null,"tir3":null,"tir4":null,"tir5":null}},"vnir":{"mean_radiance":{"green":null,"nir":null,"red":null},"pixel_counts":{"cloud":1916.0,"lake":0.0,"valid":{"green":1916,"nir":1916,"red":1916}}}},"type":"Feature"},{"geometry":{"coordinates":[[[102.632858,-3.5107590000000015],[102.625713,-3.511090000000001],[102.625142,-3.515787],[102.632956,-3.515446000000001],[102.632858,-3.5107590000000015]]],"geodesic":true,"type":"Polygon"},"id":"20010210034727","properties":{"AOT":0.164,"H2O":4.789999389648438,"O3":0.248,"date":{"type":"Date","value":981776847000},"doy":41.15795138888889,"solar_z":26.412183,"swir":{"swir1":null,"swir2":null,"swir3":null,"swir4":null,"swir5":null,"swir6":null},"tir":{"bkgd_rad":{"tir1":null,"tir2":null,"tir3":null,"tir4":null,"tir5":null},"lake_rad":{"tir1":null,"tir2":null,"tir3":null,"tir4":null,"tir5":null}},"vnir":{"mean_radiance":{"green":null,"nir":null,"red":null},"pixel_counts":{"cloud":1916.0,"lake":0.0,"valid":{"green":1916,"nir":1916,"red":1916}}}},"type":"Feature"},{"geometry":{"coordinates":[[[102.632858,-3.5107590000000015],[102.625713,-3.511090000000001],[102.625142,-3.515787],[102.632956,-3.515446000000001],[102.632858,-3.5107590000000015]]],"geodesic":true,"type":"Polygon"},"id":"20010524035103","properties":{"AOT":0.093,"H2O":4.25,"O3":0.25,"date":{"type":"Date","value":990676263000},"doy":144.1604513888889,"solar_z":30.459621,"swir":{"swir1":null,"swir2":null,"swir3":null,"swir4":null,"swir5":null,"swir6":null},"tir":{"bkgd_rad":{"tir1":6.866469333333333,"tir2":7.462017777777778,"tir3":7.947784074074074,"tir4":8.184425481481483,"tir5":7.9183907407407395},"lake_rad":{"tir1":null,"tir2":null,"tir3":null,"tir4":null,"tir5":null}},"vnir":{"mean_radiance":{"green":null,"nir":null,"red":null},"pixel_counts":{"cloud":1916.0,"lake":0.0,"valid":{"green":1916,"nir":1916,"red":1916}}}},"type":"Feature"},{"geometry":{"coordinates":[[[102.632858,-3.5107590000000015],[102.625713,-3.511090000000001],[102.625142,-3.515787],[102.632956,-3.515446000000001],[102.632858,-3.5107590000000015]]],"geodesic":true,"type":"Polygon"},"id":"20010602034446","properties":{"AOT":0.093,"H2O":4.310000610351563,"O3":0.249,"date":{"type":"Date","value":991453486000},"doy":153.15608796296297,"solar_z":32.877602,"swir":{"swir1":null,"swir2":null,"swir3":null,"swir4":null,"swir5":null,"swir6":null},"tir":{"bkgd_rad":{"tir1":null,"tir2":null,"tir3":null,"tir4":null,"tir5":null},"lake_rad":{"tir1":null,"tir2":null,"tir3":null,"tir4":null,"tir5":null}},"vnir":{"mean_radiance":{"green":null,"nir":null,"red":null},"pixel_counts":{"cloud":1916.0,"lake":0.0,"valid":{"green":1916,"nir":1916,"red":1916}}}},"type":"Feature"},{"geometry":{"coordinates":[[[102.632858,-3.5107590000000015],[102.625713,-3.511090000000001],[102.625142,-3.515787],[102.632956,-3.515446000000001],[102.632858,-3.5107590000000015]]],"geodesic":true,"type":"Polygon"},"id":"20020204034337","properties":{"AOT":0.287,"H2O":4.7,"O3":0.275,"date":{"type":"Date","value":1012794217000},"doy":35.15528935185185,"solar_z":27.705511,"swir":{"swir1":null,"swir2":null,"swir3":null,"swir4":null,"swir5":null,"swir6":null},"tir":{"bkgd_rad":{"tir1":6.753673406249991,"tir2":7.350402812499997,"tir3":7.808600833333338,"tir4":7.99780511979167,"tir5":7.681294270833333},"lake_rad":{"tir1":null,"tir2":null,"tir3":null,"tir4":null,"tir5":null}},"vnir":{"mean_radiance":{"green":null,"nir":null,"red":null},"pixel_counts":{"cloud":1542.0,"lake":0.0,"valid":{"green":1916,"nir":1916,"red":1916}}}},"type":"Feature"},{"geometry":{"coordinates":[[[102.632858,-3.5107590000000015],[102.625713,-3.511090000000001],[102.625142,-3.515787],[102.632956,-3.515446000000001],[102.632858,-3.5107590000000015]]],"geodesic":true,"type":"Polygon"},"id":"20020409034245","properties":{"AOT":0.148,"H2O":4.8899993896484375,"O3":0.275,"date":{"type":"Date","value":1018323765000},"doy":99.1546875,"solar_z":24.544492000000005,"swir":{"swir1":null,"swir2":null,"swir3":null,"swir4":null,"swir5":null,"swir6":null},"tir":{"bkgd_rad":{"tir1":7.085637290322578,"tir2":7.6843645161290315,"tir3":8.125044838709679,"tir4":8.342632387096776,"tir5":8.038241129032258},"lake_rad":{"tir1":null,"tir2":null,"tir3":null,"tir4":null,"tir5":null}},"vnir":{"mean_radiance":{"green":null,"nir":null,"red":null},"pixel_counts":{"cloud":1916.0,"lake":0.0,"valid":{"green":1916,"nir":1916,"red":1916}}}},"type":"Feature"},{"geometry":{"coordinates":[[[102.632858,-3.5107590000000015],[102.625713,-3.511090000000001],[102.625142,-3.515787],[102.632956,-3.515446000000001],[102.632858,-3.5107590000000015]]],"geodesic":true,"type":"Polygon"},"id":"20020511034259","properties":{"AOT":0.131,"H2O":4.710000610351562,"O3":0.25817142857142855,"date":{"type":"Date","value":1021088579000},"doy":131.15484953703702,"solar_z":29.263632,"swir":{"swir1":null,"swir2":null,"swir3":null,"swir4":null,"swir5":null,"swir6":null},"tir":{"bkgd_rad":{"tir1":7.008922799999999,"tir2":7.62072,"tir3":8.055616,"tir4":8.3015326,"tir5":8.0146275},"lake_rad":{"tir1":null,"tir2":null,"tir3":null,"tir4":null,"tir5":null}},"vnir":{"mean_radiance":{"green":null,"nir":null,"red":null},"pixel_counts":{"cloud":1916.0,"lake":0.0,"valid":{"green":1916,"nir":1916,"red":1916}}}},"type":"Feature"},{"geometry":{"coordinates":[[[102.632858,-3.5107590000000015],[102.625713,-3.511090000000001],[102.625142,-3.515787],[102.632956,-3.515446000000001],[102.632858,-3.5107590000000015]]],"geodesic":true,"type":"Polygon"},"id":"20020628034307","properties":{"AOT":0.113,"H2O":4.210000610351562,"O3":0.255,"date":{"type":"Date","value":1025235787000},"doy":179.15494212962963,"solar_z":34.550998,"swir":{"swir1":null,"swir2":null,"swir3":null,"swir4":null,"swir5":null,"swir6":null},"tir":{"bkgd_rad":{"tir1":7.452322253731341,"tir2":8.04730343283582,"tir3":8.491952686567164,"tir4":8.73106520149254,"tir5":8.411197201492534},"lake_rad":{"tir1":null,"tir2":null,"tir3":null,"tir4":null,"tir5":null}},"vnir":{"mean_radiance":{"green":null,"nir":null,"red":null},"pixel_counts":{"cloud":1363.0,"lake":0.0,"valid":{"green":1916,"nir":1916,"red":1916}}}},"type":"Feature"},{"geometry":{"coordinates":[[[102.632858,-3.5107590000000015],[102.625713,-3.511090000000001],[102.625142,-3.515787],[102.632956,-3.515446000000001],[102.632858,-3.5107590000000015]]],"geodesic":true,"type":"Polygon"},"id":"20020714034315","properties":{"AOT":0.113,"H2O":4.1,"O3":0.261,"date":{"type":"Date","value":1026618195000},"doy":195.1550347222222,"solar_z":33.721338,"swir":{"swir1":null,"swir2":null,"swir3":null,"swir4":null,"swir5":null,"swir6":null},"tir":{"bkgd_rad":{"tir1":null,"tir2":null,"tir3":null,"tir4":null,"tir5":null},"lake_rad":{"tir1":null,"tir2":null,"tir3":null,"tir4":null,"tir5":null}},"vnir":{"mean_radiance":{"green":null,"nir":null,"red":null},"pixel_counts":{"cloud":1916.0,"lake":0.0,"valid":{"green":1916,"nir":1916,"red":1916}}}},"type":"Feature"},{"geometry":{"coordinates":[[[102.632858,-3.5107590000000015],[102.625713,-3.511090000000001],[102.625142,-3.515787],[102.632956,-3.515446000000001],[102.632858,-3.5107590000000015]]],"geodesic":true,"type":"Polygon"},"id":"20020909033656","properties":{"AOT":0.779,"H2O":4.019999694824219,"O3":0.272,"date":{"type":"Date","value":1031542616000},"doy":252.15064814814815,"solar_z":24.510538999999994,"swir":{"swir1":null,"swir2":null,"swir3":null,"swir4":null,"swir5":null,"swir6":null},"tir":{"bkgd_rad":{"tir1":null,"tir2":null,"tir3":null,"tir4":null,"tir5":null},"lake_rad":{"tir1":null,"tir2":null,"tir3":null,"tir4":null,"tir5":null}},"vnir":{"mean_radiance":{"green":null,"nir":null,"red":null},"pixel_counts":{"cloud":1916.0,"lake":0.0,"valid":{"green":1916,"nir":1916,"red":1916}}}},"type":"Feature"},{"geometry":{"coordinates":[[[102.632858,-3.5107590000000015],[102.625713,-3.511090000000001],[102.625142,-3.515787],[102.632956,-3.515446000000001],[102.632858,-3.5107590000000015]]],"geodesic":true,"type":"Polygon"},"id":"20021230033637","properties":{"AOT":0.124,"H2O":5.130000305175781,"O3":0.251,"date":{"type":"Date","value":1041219397000},"doy":364.1504282407407,"solar_z":29.910095,"swir":{"swir1":null,"swir2":null,"swir3":null,"swir4":null,"swir5":null,"swir6":null},"tir":{"bkgd_rad":{"tir1":null,"tir2":null,"tir3":null,"tir4":null,"tir5":null},"lake_rad":{"tir1":null,"tir2":null,"tir3":null,"tir4":null,"tir5":null}},"vnir":{"mean_radiance":{"green":null,"nir":null,"red":null},"pixel_counts":{"cloud":1916.0,"lake":0.0,"valid":{"green":1916,"nir":1916,"red":1916}}}},"type":"Feature"},{"geometry":{"coordinates":[[[102.632858,-3.5107590000000015],[102.625713,-3.511090000000001],[102.625142,-3.515787],[102.632956,-3.515446000000001],[102.632858,-3.5107590000000015]]],"geodesic":true,"type":"Polygon"},"id":"20030412034208","properties":{"AOT":0.135,"H2O":4.689999389648437,"O3":0.259,"date":{"type":"Date","value":1050118928000},"doy":102.15425925925926,"solar_z":25.205697999999998,"swir":{"swir1":null,"swir2":null,"swir3":null,"swir4":null,"swir5":null,"swir6":null},"tir":{"bkgd_rad":{"tir1":null,"tir2":null,"tir3":null,"tir4":null,"tir5":null},"lake_rad":{"tir1":null,"tir2":null,"tir3":null,"tir4":null,"tir5":null}},"vnir":{"mean_radiance":{"green":null,"nir":null,"red":null},"pixel_counts":{"cloud":1916.0,"lake":0.0,"valid":{"green":1916,"nir":1916,"red":1916}}}},"type":"Feature"},{"geometry":{"coordinates":[[[102.632858,-3.5107590000000015],[102.625713,-3.511090000000001],[102.625142,-3.515787],[102.632956,-3.515446000000001],[102.632858,-3.5107590000000015]]],"geodesic":true,"type":"Polygon"},"id":"20030514034150","properties":{"AOT":0.173,"H2O":4.269999694824219,"O3":0.248,"date":{"type":"Date","value":1052883710000},"doy":134.15405092592593,"solar_z":30.129804999999998,"swir":{"swir1":null,"swir2":null,"swir3":null,"swir4":null,"swir5":null,"swir6":null},"tir":{"bkgd_rad":{"tir1":null,"tir2":null,"tir3":null,"tir4":null,"tir5":null},"lake_rad":{"tir1":null,"tir2":null,"tir3":null,"tir4":null,"tir5":null}},"vnir":{"mean_radiance":{"green":null,"nir":null,"red":null},"pixel_counts":{"cloud":1916.0,"lake":0.0,"valid":{"green":1916,"nir":1916,"red":1916}}}},"type":"Feature"},{"geometry":{"coordinates":[[[102.632858,-3.5107590000000015],[102.625713,-3.511090000000001],[102.625142,-3.515787],[102.632956,-3.515446000000001],[102.632858,-3.5107590000000015]]],"geodesic":true,"type":"Polygon"},"id":"20031005034122","properties":{"AOT":0.236,"H2O":4.8,"O3":0.273,"date":{"type":"Date","value":1065325282000},"doy":278.15372685185184,"solar_z":19.216553000000005,"swir":{"swir1":null,"swir2":null,"swir3":null,"swir4":null,"swir5":null,"swir6":null},"tir":{"bkgd_rad":{"tir1":null,"tir2":null,"tir3":null,"tir4":null,"tir5":null},"lake_rad":{"tir1":null,"tir2":null,"tir3":null,"tir4":null,"tir5":null}},"vnir":{"mean_radiance":{"green":null,"nir":null,"red":null},"pixel_counts":{"cloud":1916.0,"lake":0.0,"valid":{"green":1916,"nir":1916,"red":1916}}}},"type":"Feature"},{"geometry":{"coordinates":[[[102.632858,-3.5107590000000015],[102.625713,-3.511090000000001],[102.625142,-3.515787],[102.632956,-3.515446000000001],[102.632858,-3.5107590000000015]]],"geodesic":true,"type":"Polygon"},"id":"20040210034213","properties":{"AOT":0.128,"H2O":4.1100006103515625,"O3":0.264,"date":{"type":"Date","value":1076384533000},"doy":41.15431712962963,"solar_z":27.451931000000002,"swir":{"swir1":7.464066666666667,"swir2":2.2550399999999997,"swir3":1.9583333333333333,"swir4":1.8745800000000001,"swir5":1.2315399999999999,"swir6":0.88404},"tir":{"bkgd_rad":{"tir1":7.491430615384614,"tir2":8.143996923076923,"tir3":8.639095726495729,"tir4":8.84186155555556,"tir5":8.493706410256411},"lake_rad":{"tir1":7.797546,"tir2":8.522459999999999,"tir3":9.05466,"tir4":9.245432000000001,"tir5":8.835474999999999}},"vnir":{"mean_radiance":{"green":165.0957551020408,"nir":71.32297959183674,"red":138.99918367346933},"pixel_counts":{"cloud":1338.0,"lake":56.0,"valid":{"green":1916,"nir":1916,"red":1916}}}},"type":"Feature"},{"geometry":{"coordinates":[[[102.632858,-3.5107590000000015],[102.625713,-3.511090000000001],[102.625142,-3.515787],[102.632956,-3.515446000000001],[102.632858,-3.5107590000000015]]],"geodesic":true,"type":"Polygon"},"id":"20040414034125","properties":{"AOT":0.167,"H2O":4.380000305175781,"O3":0.272,"date":{"type":"Date","value":1081914085000},"doy":105.15376157407407,"solar_z":25.375364000000005,"swir":{"swir1":null,"swir2":null,"swir3":null,"swir4":null,"swir5":null,"swir6":null},"tir":{"bkgd_rad":{"tir1":7.791443410909087,"tir2":8.382816654545461,"tir3":8.799351418181818,"tir4":8.905880778181814,"tir5":8.514660000000001},"lake_rad":{"tir1":null,"tir2":null,"tir3":null,"tir4":null,"tir5":null}},"vnir":{"mean_radiance":{"green":null,"nir":null,"red":null},"pixel_counts":{"cloud":188.0,"lake":0.0,"valid":{"green":1916,"nir":1916,"red":1916}}}},"type":"Feature"},{"geometry":{"coordinates":[[[102.632858,-3.5107590000000015],[102.625713,-3.511090000000001],[102.625142,-3.515787],[102.632956,-3.515446000000001],[102.632858,-3.5107590000000015]]],"geodesic":true,"type":"Polygon"},"id":"20040423033530","properties":{"AOT":0.171,"H2O":4.369999694824219,"O3":0.2579416666666667,"date":{"type":"Date","value":1082691330000},"doy":114.14965277777777,"solar_z":28.251894999999998,"swir":{"swir1":null,"swir2":null,"swir3":null,"swir4":null,"swir5":null,"swir6":null},"tir":{"bkgd_rad":{"tir1":null,"tir2":null,"tir3":null,"tir4":null,"tir5":null},"lake_rad":{"tir1":null,"tir2":null,"tir3":null,"tir4":null,"tir5":null}},"vnir":{"mean_radiance":{"green":null,"nir":null,"red":null},"pixel_counts":{"cloud":1916.0,"lake":0.0,"valid":{"green":1916,"nir":1916,"red":1916}}}},"type":"Feature"},{"geometry":{"coordinates":[[[102.632858,-3.5107590000000015],[102.625713,-3.511090000000001],[102.625142,-3.515787],[102.632956,-3.515446000000001],[102.632858,-3.5107590000000015]]],"geodesic":true,"type":"Polygon"},"id":"20040703034115","properties":{"AOT":0.171,"H2O":4.089999389648438,"O3":0.273,"date":{"type":"Date","value":1088826075000},"doy":185.15364583333334,"solar_z":34.601861,"swir":{"swir1":null,"swir2":null,"swir3":null,"swir4":null,"swir5":null,"swir6":null},"tir":{"bkgd_rad":{"tir1":null,"tir2":null,"tir3":null,"tir4":null,"tir5":null},"lake_rad":{"tir1":null,"tir2":null,"tir3":null,"tir4":null,"tir5":null}},"vnir":{"mean_radiance":{"green":null,"nir":null,"red":null},"pixel_counts":{"cloud":1916.0,"lake":0.0,"valid":{"green":1916,"nir":1916,"red":1916}}}},"type":"Feature"},{"geometry":{"coordinates":[[[102.632858,-3.5107590000000015],[102.625713,-3.511090000000001],[102.625142,-3.515787],[102.632956,-3.515446000000001],[102.632858,-3.5107590000000015]]],"geodesic":true,"type":"Polygon"},"id":"20040829033450","properties":{"AOT":0.331,"H2O":3.7899993896484374,"O3":0.277,"date":{"type":"Date","value":1093750490000},"doy":242.1491898148148,"solar_z":27.404775,"swir":{"swir1":null,"swir2":null,"swir3":null,"swir4":null,"swir5":null,"swir6":null},"tir":{"bkgd_rad":{"tir1":8.339516000000001,"tir2":8.91092888888889,"tir3":9.331195925925925,"tir4":9.487806203703702,"tir5":9.077566666666668},"lake_rad":{"tir1":null,"tir2":null,"tir3":null,"tir4":null,"tir5":null}},"vnir":{"mean_radiance":{"green":null,"nir":null,"red":null},"pixel_counts":{"cloud":1674.0,"lake":0.0,"valid":{"green":1916,"nir":1916,"red":1916}}}},"type":"Feature"},{"geometry":{"coordinates":[[[102.632858,-3.5107590000000015],[102.625713,-3.511090000000001],[102.625142,-3.515787],[102.632956,-3.515446000000001],[102.632858,-3.5107590000000015]]],"geodesic":true,"type":"Polygon"},"id":"20040914033450","properties":{"AOT":0.331,"H2O":4.1100006103515625,"O3":0.277,"date":{"type":"Date","value":1095132890000},"doy":258.1491898148148,"solar_z":23.661118000000002,"swir":{"swir1":null,"swir2":null,"swir3":null,"swir4":null,"swir5":null,"swir6":null},"tir":{"bkgd_rad":{"tir1":7.804368,"tir2":8.39364,"tir3":8.777880000000001,"tir4":9.112595333333333,"tir5":8.729233333333333},"lake_rad":{"tir1":null,"tir2":null,"tir3":null,"tir4":null,"tir5":null}},"vnir":{"mean_radiance":{"green":null,"nir":null,"red":null},"pixel_counts":{"cloud":1746.0,"lake":0.0,"valid":{"green":1916,"nir":1916,"red":1916}}}},"type":"Feature"},{"geometry":{"coordinates":[[[102.632858,-3.5107590000000015],[102.625713,-3.511090000000001],[102.625142,-3.515787],[102.632956,-3.515446000000001],[102.632858,-3.5107590000000015]]],"geodesic":true,"type":"Polygon"},"id":"20041101033422","properties":{"AOT":0.243,"H2O":4.469999694824219,"O3":0.276,"date":{"type":"Date","value":1099280062000},"doy":306.14886574074075,"solar_z":22.348782,"swir":{"swir1":null,"swir2":null,"swir3":null,"swir4":null,"swir5":null,"swir6":null},"tir":{"bkgd_rad":{"tir1":null,"tir2":null,"tir3":null,"tir4":null,"tir5":null},"lake_rad":{"tir1":null,"tir2":null,"tir3":null,"tir4":null,"tir5":null}},"vnir":{"mean_radiance":{"green":null,"nir":null,"red":null},"pixel_counts":{"cloud":1916.0,"lake":0.0,"valid":{"green":1916,"nir":1916,"red":1916}}}},"type":"Feature"},{"geometry":{"coordinates":[[[102.632858,-3.5107590000000015],[102.625713,-3.511090000000001],[102.625142,-3.515787],[102.632956,-3.515446000000001],[102.632858,-3.5107590000000015]]],"geodesic":true,"type":"Polygon"},"id":"20050309033449","properties":{"AOT":0.21,"H2O":4.210000610351562,"O3":0.274,"date":{"type":"Date","value":1110339289000},"doy":68.14917824074074,"solar_z":26.288826999999998,"swir":{"swir1":null,"swir2":null,"swir3":null,"swir4":null,"swir5":null,"swir6":null},"tir":{"bkgd_rad":{"tir1":null,"tir2":null,"tir3":null,"tir4":null,"tir5":null},"lake_rad":{"tir1":null,"tir2":null,"tir3":null,"tir4":null,"tir5":null}},"vnir":{"mean_radiance":{"green":null,"nir":null,"red":null},"pixel_counts":{"cloud":1916.0,"lake":0.0,"valid":{"green":1916,"nir":1916,"red":1916}}}},"type":"Feature"},{"geometry":{"coordinates":[[[102.632858,-3.5107590000000015],[102.625713,-3.511090000000001],[102.625142,-3.515787],[102.632956,-3.515446000000001],[102.632858,-3.5107590000000015]]],"geodesic":true,"type":"Polygon"},"id":"20070626034137","properties":{"AOT":0.166,"H2O":3.9100006103515623,"O3":0.239,"date":{"type":"Date","value":1182829297000},"doy":177.15390046296295,"solar_z":34.733983,"swir":{"swir1":null,"swir2":null,"swir3":null,"swir4":null,"swir5":null,"swir6":null},"tir":{"bkgd_rad":{"tir1":8.0295184516129,"tir2":8.633102795698921,"tir3":9.059950896057355,"tir4":9.270285311827962,"tir5":8.946080197132622},"lake_rad":{"tir1":null,"tir2":null,"tir3":null,"tir4":null,"tir5":null}},"vnir":{"mean_radiance":{"green":null,"nir":null,"red":null},"pixel_counts":{"cloud":0.0,"lake":0.0,"valid":{"green":1916,"nir":1916,"red":1916}}}},"type":"Feature"},{"geometry":{"coordinates":[[[102.632858,-3.5107590000000015],[102.625713,-3.511090000000001],[102.625142,-3.515787],[102.632956,-3.515446000000001],[102.632858,-3.5107590000000015]]],"geodesic":true,"type":"Polygon"},"id":"20070923033541","properties":{"AOT":0.556,"H2O":3.9399993896484373,"O3":0.252,"date":{"type":"Date","value":1190518541000},"doy":266.1497800925926,"solar_z":21.948319999999995,"swir":{"swir1":null,"swir2":null,"swir3":null,"swir4":null,"swir5":null,"swir6":null},"tir":{"bkgd_rad":{"tir1":null,"tir2":null,"tir3":null,"tir4":null,"tir5":null},"lake_rad":{"tir1":null,"tir2":null,"tir3":null,"tir4":null,"tir5":null}},"vnir":{"mean_radiance":{"green":null,"nir":null,"red":null},"pixel_counts":{"cloud":1916.0,"lake":0.0,"valid":{"green":1916,"nir":1916,"red":1916}}}},"type":"Feature"},{"geometry":{"coordinates":[[[102.632858,-3.5107590000000015],[102.625713,-3.511090000000001],[102.625142,-3.515787],[102.632956,-3.515446000000001],[102.632858,-3.5107590000000015]]],"geodesic":true,"type":"Polygon"},"id":"20071203034124","properties":{"AOT":0.228,"H2O":4.830000305175782,"O3":0.253,"date":{"type":"Date","value":1196653284000},"doy":337.15375,"solar_z":26.423625,"swir":{"swir1":null,"swir2":null,"swir3":null,"swir4":null,"swir5":null,"swir6":null},"tir":{"bkgd_rad":{"tir1":null,"tir2":null,"tir3":null,"tir4":null,"tir5":null},"lake_rad":{"tir1":null,"tir2":null,"tir3":null,"tir4":null,"tir5":null}},"vnir":{"mean_radiance":{"green":null,"nir":null,"red":null},"pixel_counts":{"cloud":1916.0,"lake":0.0,"valid":{"green":1916,"nir":1916,"red":1916}}}},"type":"Feature"},{"geometry":{"coordinates":[[[102.632858,-3.5107590000000015],[102.625713,-3.511090000000001],[102.625142,-3.515787],[102.632956,-3.515446000000001],[102.632858,-3.5107590000000015]]],"geodesic":true,"type":"Polygon"},"id":"20080628034156","properties":{"AOT":0.184,"H2O":4.05,"O3":0.264,"date":{"type":"Date","value":1214624516000},"doy":180.15412037037038,"solar_z":34.734726,"swir":false,"tir":{"bkgd_rad":{"tir1":null,"tir2":null,"tir3":null,"tir4":null,"tir5":null},"lake_rad":{"tir1":null,"tir2":null,"tir3":null,"tir4":null,"tir5":null}},"vnir":{"mean_radiance":{"green":null,"nir":null,"red":null},"pixel_counts":{"cloud":1916.0,"lake":0.0,"valid":{"green":1916,"nir":1916,"red":1916}}}},"type":"Feature"},{"geometry":{"coordinates":[[[102.632858,-3.5107590000000015],[102.625713,-3.511090000000001],[102.625142,-3.515787],[102.632956,-3.515446000000001],[102.632858,-3.5107590000000015]]],"geodesic":true,"type":"Polygon"},"id":"20080824033551","properties":{"AOT":0.268,"H2O":4.569999694824219,"O3":0.261,"date":{"type":"Date","value":1219548951000},"doy":237.14989583333335,"solar_z":28.289074999999997,"swir":false,"tir":{"bkgd_rad":{"tir1":null,"tir2":null,"tir3":null,"tir4":null,"tir5":null},"lake_rad":{"tir1":null,"tir2":null,"tir3":null,"tir4":null,"tir5":null}},"vnir":{"mean_radiance":{"green":null,"nir":null,"red":null},"pixel_counts":{"cloud":1916.0,"lake":0.0,"valid":{"green":1916,"nir":1916,"red":1916}}}},"type":"Feature"},{"geometry":{"coordinates":[[[102.632858,-3.5107590000000015],[102.625713,-3.511090000000001],[102.625142,-3.515787],[102.632956,-3.515446000000001],[102.632858,-3.5107590000000015]]],"geodesic":true,"type":"Polygon"},"id":"20080916034154","properties":{"AOT":0.171,"H2O":4.669999694824218,"O3":0.258,"date":{"type":"Date","value":1221536514000},"doy":260.1540972222222,"solar_z":21.616411,"swir":false,"tir":{"bkgd_rad":{"tir1":null,"tir2":null,"tir3":null,"tir4":null,"tir5":null},"lake_rad":{"tir1":null,"tir2":null,"tir3":null,"tir4":null,"tir5":null}},"vnir":{"mean_radiance":{"green":null,"nir":null,"red":null},"pixel_counts":{"cloud":1916.0,"lake":0.0,"valid":{"green":1916,"nir":1916,"red":1916}}}},"type":"Feature"},{"geometry":{"coordinates":[[[102.632858,-3.5107590000000015],[102.625713,-3.511090000000001],[102.625142,-3.515787],[102.632956,-3.515446000000001],[102.632858,-3.5107590000000015]]],"geodesic":true,"type":"Polygon"},"id":"20080925033550","properties":{"AOT":0.171,"H2O":3.8699996948242186,"O3":0.266,"date":{"type":"Date","value":1222313750000},"doy":269.14988425925924,"solar_z":21.582943999999998,"swir":false,"tir":{"bkgd_rad":{"tir1":6.706026,"tir2":7.210529999999999,"tir3":7.573557500000001,"tir4":7.90615375,"tir5":7.6611562499999994},"lake_rad":{"tir1":null,"tir2":null,"tir3":null,"tir4":null,"tir5":null}},"vnir":{"mean_radiance":{"green":null,"nir":null,"red":null},"pixel_counts":{"cloud":1916.0,"lake":0.0,"valid":{"green":1916,"nir":1916,"red":1916}}}},"type":"Feature"},{"geometry":{"coordinates":[[[102.632858,-3.5107590000000015],[102.625713,-3.511090000000001],[102.625142,-3.515787],[102.632956,-3.515446000000001],[102.632858,-3.5107590000000015]]],"geodesic":true,"type":"Polygon"},"id":"20081018034146","properties":{"AOT":0.08,"H2O":5.019999694824219,"O3":0.254,"date":{"type":"Date","value":1224301306000},"doy":292.15400462962964,"solar_z":19.163787999999997,"swir":false,"tir":{"bkgd_rad":{"tir1":null,"tir2":null,"tir3":null,"tir4":null,"tir5":null},"lake_rad":{"tir1":null,"tir2":null,"tir3":null,"tir4":null,"tir5":null}},"vnir":{"mean_radiance":{"green":null,"nir":null,"red":null},"pixel_counts":{"cloud":1916.0,"lake":0.0,"valid":{"green":1916,"nir":1916,"red":1916}}}},"type":"Feature"},{"geometry":{"coordinates":[[[102.632858,-3.5107590000000015],[102.625713,-3.511090000000001],[102.625142,-3.515787],[102.632956,-3.515446000000001],[102.632858,-3.5107590000000015]]],"geodesic":true,"type":"Polygon"},"id":"20081112033541","properties":{"AOT":0.08,"H2O":4.760000610351563,"O3":0.242,"date":{"type":"Date","value":1226460941000},"doy":317.1497800925926,"solar_z":23.888937,"swir":false,"tir":{"bkgd_rad":{"tir1":null,"tir2":null,"tir3":null,"tir4":null,"tir5":null},"lake_rad":{"tir1":null,"tir2":null,"tir3":null,"tir4":null,"tir5":null}},"vnir":{"mean_radiance":{"green":null,"nir":null,"red":null},"pixel_counts":{"cloud":1916.0,"lake":0.0,"valid":{"green":1916,"nir":1916,"red":1916}}}},"type":"Feature"},{"geometry":{"coordinates":[[[102.632858,-3.5107590000000015],[102.625713,-3.511090000000001],[102.625142,-3.515787],[102.632956,-3.515446000000001],[102.632858,-3.5107590000000015]]],"geodesic":true,"type":"Polygon"},"id":"20081119034150","properties":{"AOT":0.111,"H2O":4.65,"O3":0.24,"date":{"type":"Date","value":1227066110000},"doy":324.1540509259259,"solar_z":24.188345999999996,"swir":false,"tir":{"bkgd_rad":{"tir1":null,"tir2":null,"tir3":null,"tir4":null,"tir5":null},"lake_rad":{"tir1":null,"tir2":null,"tir3":null,"tir4":null,"tir5":null}},"vnir":{"mean_radiance":{"green":null,"nir":null,"red":null},"pixel_counts":{"cloud":1916.0,"lake":0.0,"valid":{"green":1916,"nir":1916,"red":1916}}}},"type":"Feature"},{"geometry":{"coordinates":[[[102.632858,-3.5107590000000015],[102.625713,-3.511090000000001],[102.625142,-3.515787],[102.632956,-3.515446000000001],[102.632858,-3.5107590000000015]]],"geodesic":true,"type":"Polygon"},"id":"20081128033556","properties":{"AOT":0.111,"H2O":4.3899993896484375,"O3":0.246,"date":{"type":"Date","value":1227843356000},"doy":333.1499537037037,"solar_z":26.713185000000003,"swir":false,"tir":{"bkgd_rad":{"tir1":7.501907360655741,"tir2":8.136333442622943,"tir3":8.615452704918034,"tir4":8.842348934426234,"tir5":8.484629098360651},"lake_rad":{"tir1":null,"tir2":null,"tir3":null,"tir4":null,"tir5":null}},"vnir":{"mean_radiance":{"green":null,"nir":null,"red":null},"pixel_counts":{"cloud":1916.0,"lake":0.0,"valid":{"green":1916,"nir":1916,"red":1916}}}},"type":"Feature"},{"geometry":{"coordinates":[[[102.632858,-3.5107590000000015],[102.625713,-3.511090000000001],[102.625142,-3.515787],[102.632956,-3.515446000000001],[102.632858,-3.5107590000000015]]],"geodesic":true,"type":"Polygon"},"id":"20090514034227","properties":{"AOT":0.053,"H2O":4.580000305175782,"O3":0.249,"date":{"type":"Date","value":1242272547000},"doy":134.15447916666668,"solar_z":30.133735,"swir":false,"tir":{"bkgd_rad":{"tir1":null,"tir2":null,"tir3":null,"tir4":null,"tir5":null},"lake_rad":{"tir1":null,"tir2":null,"tir3":null,"tir4":null,"tir5":null}},"vnir":{"mean_radiance":{"green":null,"nir":null,"red":null},"pixel_counts":{"cloud":1916.0,"lake":0.0,"valid":{"green":1916,"nir":1916,"red":1916}}}},"type":"Feature"},{"geometry":{"coordinates":[[[102.632858,-3.5107590000000015],[102.625713,-3.511090000000001],[102.625142,-3.515787],[102.632956,-3.515446000000001],[102.632858,-3.5107590000000015]]],"geodesic":true,"type":"Polygon"},"id":"20090530034219","properties":{"AOT":0.124,"H2O":4.169999694824218,"O3":0.253,"date":{"type":"Date","value":1243654939000},"doy":150.15438657407407,"solar_z":32.580452,"swir":false,"tir":{"bkgd_rad":{"tir1":7.810242499999997,"tir2":8.448633333333333,"tir3":8.901442500000003,"tir4":9.119395305555559,"tir5":8.711090972222223},"lake_rad":{"tir1":null,"tir2":null,"tir3":null,"tir4":null,"tir5":null}},"vnir":{"mean_radiance":{"green":null,"nir":null,"red":null},"pixel_counts":{"cloud":1916.0,"lake":0.0,"valid":{"green":1916,"nir":1916,"red":1916}}}},"type":"Feature"},{"geometry":{"coordinates":[[[102.632858,-3.5107590000000015],[102.625713,-3.511090000000001],[102.625142,-3.515787],[102.632956,-3.515446000000001],[102.632858,-3.5107590000000015]]],"geodesic":true,"type":"Polygon"},"id":"20090615034208","properties":{"AOT":0.124,"H2O":4.7,"O3":0.251,"date":{"type":"Date","value":1245037328000},"doy":166.15425925925925,"solar_z":34.377247,"swir":false,"tir":{"bkgd_rad":{"tir1":7.409503006993008,"tir2":8.031313006993004,"tir3":8.498473216783218,"tir4":8.664228454545455,"tir5":8.296532692307693},"lake_rad":{"tir1":null,"tir2":null,"tir3":null,"tir4":null,"tir5":null}},"vnir":{"mean_radiance":{"green":null,"nir":null,"red":null},"pixel_counts":{"cloud":269.0,"lake":0.0,"valid":{"green":1916,"nir":1916,"red":1916}}}},"type":"Feature"},{"geometry":{"coordinates":[[[102.632858,-3.5107590000000015],[102.625713,-3.511090000000001],[102.625142,-3.515787],[102.632956,-3.515446000000001],[102.632858,-3.5107590000000015]]],"geodesic":true,"type":"Polygon"},"id":"20090701034154","properties":{"AOT":0.104,"H2O":4.2,"O3":0.242,"date":{"type":"Date","value":1246419714000},"doy":182.15409722222222,"solar_z":34.418945,"swir":false,"tir":{"bkgd_rad":{"tir1":7.100186,"tir2":7.683246666666666,"tir3":8.12547,"tir4":8.392747111111111,"tir5":8.114424999999999},"lake_rad":{"tir1":null,"tir2":null,"tir3":null,"tir4":null,"tir5":null}},"vnir":{"mean_radiance":{"green":null,"nir":null,"red":null},"pixel_counts":{"cloud":1916.0,"lake":0.0,"valid":{"green":1916,"nir":1916,"red":1916}}}},"type":"Feature"},{"geometry":{"coordinates":[[[102.632858,-3.5107590000000015],[102.625713,-3.511090000000001],[102.625142,-3.515787],[102.632956,-3.515446000000001],[102.632858,-3.5107590000000015]]],"geodesic":true,"type":"Polygon"},"id":"20090726033547","properties":{"AOT":0.19,"H2O":4.8,"O3":0.237,"date":{"type":"Date","value":1248579347000},"doy":207.14984953703703,"solar_z":33.636128,"swir":false,"tir":{"bkgd_rad":{"tir1":null,"tir2":null,"tir3":null,"tir4":null,"tir5":null},"lake_rad":{"tir1":null,"tir2":null,"tir3":null,"tir4":null,"tir5":null}},"vnir":{"mean_radiance":{"green":null,"nir":null,"red":null},"pixel_counts":{"cloud":1916.0,"lake":0.0,"valid":{"green":1916,"nir":1916,"red":1916}}}},"type":"Feature"},{"geometry":{"coordinates":[[[102.632858,-3.5107590000000015],[102.625713,-3.511090000000001],[102.625142,-3.515787],[102.632956,-3.515446000000001],[102.632858,-3.5107590000000015]]],"geodesic":true,"type":"Polygon"},"id":"20090811033547","properties":{"AOT":0.19,"H2O":4.410000610351562,"O3":0.248,"date":{"type":"Date","value":1249961747000},"doy":223.14984953703703,"solar_z":30.860506,"swir":false,"tir":{"bkgd_rad":{"tir1":null,"tir2":null,"tir3":null,"tir4":null,"tir5":null},"lake_rad":{"tir1":null,"tir2":null,"tir3":null,"tir4":null,"tir5":null}},"vnir":{"mean_radiance":{"green":null,"nir":null,"red":null},"pixel_counts":{"cloud":1916.0,"lake":0.0,"valid":{"green":1916,"nir":1916,"red":1916}}}},"type":"Feature"},{"geometry":{"coordinates":[[[102.632858,-3.5107590000000015],[102.625713,-3.511090000000001],[102.625142,-3.515787],[102.632956,-3.515446000000001],[102.632858,-3.5107590000000015]]],"geodesic":true,"type":"Polygon"},"id":"20100118033529","properties":{"AOT":0.049,"H2O":4.489999389648437,"O3":0.229,"date":{"type":"Date","value":1263785729000},"doy":18.149641203703705,"solar_z":30.678127000000003,"swir":false,"tir":{"bkgd_rad":{"tir1":null,"tir2":null,"tir3":null,"tir4":null,"tir5":null},"lake_rad":{"tir1":null,"tir2":null,"tir3":null,"tir4":null,"tir5":null}},"vnir":{"mean_radiance":{"green":null,"nir":null,"red":null},"pixel_counts":{"cloud":1916.0,"lake":0.0,"valid":{"green":1916,"nir":1916,"red":1916}}}},"type":"Feature"},{"geometry":{"coordinates":[[[102.632858,-3.5107590000000015],[102.625713,-3.511090000000001],[102.625142,-3.515787],[102.632956,-3.515446000000001],[102.632858,-3.5107590000000015]]],"geodesic":true,"type":"Polygon"},"id":"20100602034137","properties":{"AOT":0.042,"H2O":4.6399993896484375,"O3":0.235,"date":{"type":"Date","value":1275450097000},"doy":153.15390046296295,"solar_z":32.905562,"swir":false,"tir":{"bkgd_rad":{"tir1":7.439000015810275,"tir2":8.155080474308297,"tir3":8.630555731225298,"tir4":8.810468798418972,"tir5":8.427801086956524},"lake_rad":{"tir1":null,"tir2":null,"tir3":null,"tir4":null,"tir5":null}},"vnir":{"mean_radiance":{"green":86.697,"nir":35.1265,"red":47.436},"pixel_counts":{"cloud":260.0,"lake":105.0,"valid":{"green":1916,"nir":1916,"red":1916}}}},"type":"Feature"},{"geometry":{"coordinates":[[[102.632858,-3.5107590000000015],[102.625713,-3.511090000000001],[102.625142,-3.515787],[102.632956,-3.515446000000001],[102.632858,-3.5107590000000015]]],"geodesic":true,"type":"Polygon"},"id":"20100906034119","properties":{"AOT":0.086,"H2O":5.130000305175781,"O3":0.26,"date":{"type":"Date","value":1283744479000},"doy":249.15369212962963,"solar_z":24.103260000000006,"swir":false,"tir":{"bkgd_rad":{"tir1":null,"tir2":null,"tir3":null,"tir4":null,"tir5":null},"lake_rad":{"tir1":null,"tir2":null,"tir3":null,"tir4":null,"tir5":null}},"vnir":{"mean_radiance":{"green":null,"nir":null,"red":null},"pixel_counts":{"cloud":1916.0,"lake":0.0,"valid":{"green":1916,"nir":1916,"red":1916}}}},"type":"Feature"},{"geometry":{"coordinates":[[[102.632858,-3.5107590000000015],[102.625713,-3.511090000000001],[102.625142,-3.515787],[102.632956,-3.515446000000001],[102.632858,-3.5107590000000015]]],"geodesic":true,"type":"Polygon"},"id":"20110121033455","properties":{"AOT":0.141,"H2O":4.460000610351562,"O3":0.249,"date":{"type":"Date","value":1295580895000},"doy":21.149247685185184,"solar_z":30.504857,"swir":false,"tir":{"bkgd_rad":{"tir1":6.61137075,"tir2":7.2012075,"tir3":7.636162499999999,"tir4":7.9218095,"tir5":7.640909375000001},"lake_rad":{"tir1":null,"tir2":null,"tir3":null,"tir4":null,"tir5":null}},"vnir":{"mean_radiance":{"green":null,"nir":null,"red":null},"pixel_counts":{"cloud":1916.0,"lake":0.0,"valid":{"green":1916,"nir":1916,"red":1916}}}},"type":"Feature"},{"geometry":{"coordinates":[[[102.632858,-3.5107590000000015],[102.625713,-3.511090000000001],[102.625142,-3.515787],[102.632956,-3.515446000000001],[102.632858,-3.5107590000000015]]],"geodesic":true,"type":"Polygon"},"id":"20110206033504","properties":{"AOT":0.141,"H2O":4.719999694824219,"O3":0.254,"date":{"type":"Date","value":1296963304000},"doy":37.149351851851854,"solar_z":29.560786999999998,"swir":false,"tir":{"bkgd_rad":{"tir1":6.775621185770749,"tir2":7.376479209486164,"tir3":7.832436403162057,"tir4":8.026454940711464,"tir5":7.654666304347825},"lake_rad":{"tir1":null,"tir2":null,"tir3":null,"tir4":null,"tir5":null}},"vnir":{"mean_radiance":{"green":null,"nir":null,"red":null},"pixel_counts":{"cloud":1530.0,"lake":5.0,"valid":{"green":1916,"nir":1916,"red":1916}}}},"type":"Feature"},{"geometry":{"coordinates":[[[102.632858,-3.5107590000000015],[102.625713,-3.511090000000001],[102.625142,-3.515787],[102.632956,-3.515446000000001],[102.632858,-3.5107590000000015]]],"geodesic":true,"type":"Polygon"},"id":"20110222033510","properties":{"AOT":0.034,"H2O":3.65,"O3":0.258,"date":{"type":"Date","value":1298345710000},"doy":53.149421296296296,"solar_z":27.446153000000002,"swir":false,"tir":{"bkgd_rad":{"tir1":7.59320017105263,"tir2":8.258664473684215,"tir3":8.730709473684215,"tir4":8.946586953947369,"tir5":8.569859374999998},"lake_rad":{"tir1":null,"tir2":null,"tir3":null,"tir4":null,"tir5":null}},"vnir":{"mean_radiance":{"green":127.76400000000001,"nir":62.926,"red":99.82799999999999},"pixel_counts":{"cloud":188.0,"lake":9.0,"valid":{"green":1916,"nir":1916,"red":1916}}}},"type":"Feature"},{"geometry":{"coordinates":[[[102.632858,-3.5107590000000015],[102.625713,-3.511090000000001],[102.625142,-3.515787],[102.632956,-3.515446000000001],[102.632858,-3.5107590000000015]]],"geodesic":true,"type":"Polygon"},"id":"20110310033515","properties":{"AOT":0.034,"H2O":4.680000305175781,"O3":0.257,"date":{"type":"Date","value":1299728115000},"doy":69.14947916666667,"solar_z":26.007589000000003,"swir":false,"tir":{"bkgd_rad":{"tir1":null,"tir2":null,"tir3":null,"tir4":null,"tir5":null},"lake_rad":{"tir1":null,"tir2":null,"tir3":null,"tir4":null,"tir5":null}},"vnir":{"mean_radiance":{"green":null,"nir":null,"red":null},"pixel_counts":{"cloud":1916.0,"lake":0.0,"valid":{"green":1916,"nir":1916,"red":1916}}}},"type":"Feature"},{"geometry":{"coordinates":[[[102.632858,-3.5107590000000015],[102.625713,-3.511090000000001],[102.625142,-3.515787],[102.632956,-3.515446000000001],[102.632858,-3.5107590000000015]]],"geodesic":true,"type":"Polygon"},"id":"20110326033513","properties":{"AOT":0.086,"H2O":4.65,"O3":0.248,"date":{"type":"Date","value":1301110513000},"doy":85.14945601851852,"solar_z":25.585109000000003,"swir":false,"tir":{"bkgd_rad":{"tir1":null,"tir2":null,"tir3":null,"tir4":null,"tir5":null},"lake_rad":{"tir1":null,"tir2":null,"tir3":null,"tir4":null,"tir5":null}},"vnir":{"mean_radiance":{"green":null,"nir":null,"red":null},"pixel_counts":{"cloud":1916.0,"lake":0.0,"valid":{"green":1916,"nir":1916,"red":1916}}}},"type":"Feature"},{"geometry":{"coordinates":[[[102.632858,-3.5107590000000015],[102.625713,-3.511090000000001],[102.625142,-3.515787],[102.632956,-3.515446000000001],[102.632858,-3.5107590000000015]]],"geodesic":true,"type":"Polygon"},"id":"20110411033512","properties":{"AOT":0.086,"H2O":4.580000305175782,"O3":0.25,"date":{"type":"Date","value":1302492912000},"doy":101.14944444444444,"solar_z":26.485504,"swir":false,"tir":{"bkgd_rad":{"tir1":null,"tir2":null,"tir3":null,"tir4":null,"tir5":null},"lake_rad":{"tir1":null,"tir2":null,"tir3":null,"tir4":null,"tir5":null}},"vnir":{"mean_radiance":{"green":null,"nir":null,"red":null},"pixel_counts":{"cloud":1916.0,"lake":0.0,"valid":{"green":1916,"nir":1916,"red":1916}}}},"type":"Feature"},{"geometry":{"coordinates":[[[102.632858,-3.5107590000000015],[102.625713,-3.511090000000001],[102.625142,-3.515787],[102.632956,-3.515446000000001],[102.632858,-3.5107590000000015]]],"geodesic":true,"type":"Polygon"},"id":"20110418034119","properties":{"AOT":0.164,"H2O":4.819999694824219,"O3":0.244,"date":{"type":"Date","value":1303098079000},"doy":108.15369212962963,"solar_z":26.05175,"swir":false,"tir":{"bkgd_rad":{"tir1":null,"tir2":null,"tir3":null,"tir4":null,"tir5":null},"lake_rad":{"tir1":null,"tir2":null,"tir3":null,"tir4":null,"tir5":null}},"vnir":{"mean_radiance":{"green":null,"nir":null,"red":null},"pixel_counts":{"cloud":1916.0,"lake":0.0,"valid":{"green":1916,"nir":1916,"red":1916}}}},"type":"Feature"},{"geometry":{"coordinates":[[[102.632858,-3.5107590000000015],[102.625713,-3.511090000000001],[102.625142,-3.515787],[102.632956,-3.515446000000001],[102.632858,-3.5107590000000015]]],"geodesic":true,"type":"Polygon"},"id":"20110427033521","properties":{"AOT":0.164,"H2O":5.569999694824219,"O3":0.249,"date":{"type":"Date","value":1303875321000},"doy":117.14954861111111,"solar_z":28.534157,"swir":false,"tir":{"bkgd_rad":{"tir1":null,"tir2":null,"tir3":null,"tir4":null,"tir5":null},"lake_rad":{"tir1":null,"tir2":null,"tir3":null,"tir4":null,"tir5":null}},"vnir":{"mean_radiance":{"green":null,"nir":null,"red":null},"pixel_counts":{"cloud":1916.0,"lake":0.0,"valid":{"green":1916,"nir":1916,"red":1916}}}},"type":"Feature"},{"geometry":{"coordinates":[[[102.632858,-3.5107590000000015],[102.625713,-3.511090000000001],[102.625142,-3.515787],[102.632956,-3.515446000000001],[102.632858,-3.5107590000000015]]],"geodesic":true,"type":"Polygon"},"id":"20110504034125","properties":{"AOT":0.164,"H2O":4.380000305175781,"O3":0.253,"date":{"type":"Date","value":1304480485000},"doy":124.15376157407407,"solar_z":28.535994000000002,"swir":false,"tir":{"bkgd_rad":{"tir1":6.06025838297872,"tir2":6.543661702127662,"tir3":6.94029822695035,"tir4":7.112737297872339,"tir5":6.806285106382975},"lake_rad":{"tir1":null,"tir2":null,"tir3":null,"tir4":null,"tir5":null}},"vnir":{"mean_radiance":{"green":null,"nir":null,"red":null},"pixel_counts":{"cloud":1901.0,"lake":0.0,"valid":{"green":1916,"nir":1916,"red":1916}}}},"type":"Feature"},{"geometry":{"coordinates":[[[102.632858,-3.5107590000000015],[102.625713,-3.511090000000001],[102.625142,-3.515787],[102.632956,-3.515446000000001],[102.632858,-3.5107590000000015]]],"geodesic":true,"type":"Polygon"},"id":"20110513033522","properties":{"AOT":0.164,"H2O":4.45,"O3":0.26,"date":{"type":"Date","value":1305257722000},"doy":133.14956018518518,"solar_z":31.288214000000004,"swir":false,"tir":{"bkgd_rad":{"tir1":null,"tir2":null,"tir3":null,"tir4":null,"tir5":null},"lake_rad":{"tir1":null,"tir2":null,"tir3":null,"tir4":null,"tir5":null}},"vnir":{"mean_radiance":{"green":null,"nir":null,"red":null},"pixel_counts":{"cloud":1916.0,"lake":0.0,"valid":{"green":1916,"nir":1916,"red":1916}}}},"type":"Feature"},{"geometry":{"coordinates":[[[102.632858,-3.5107590000000015],[102.625713,-3.511090000000001],[102.625142,-3.515787],[102.632956,-3.515446000000001],[102.632858,-3.5107590000000015]]],"geodesic":true,"type":"Polygon"},"id":"20110621034107","properties":{"AOT":0.138,"H2O":4.339999389648438,"O3":0.25,"date":{"type":"Date","value":1308627667000},"doy":172.15355324074073,"solar_z":34.555081,"swir":false,"tir":{"bkgd_rad":{"tir1":null,"tir2":null,"tir3":null,"tir4":null,"tir5":null},"lake_rad":{"tir1":null,"tir2":null,"tir3":null,"tir4":null,"tir5":null}},"vnir":{"mean_radiance":{"green":null,"nir":null,"red":null},"pixel_counts":{"cloud":1916.0,"lake":0.0,"valid":{"green":1916,"nir":1916,"red":1916}}}},"type":"Feature"},{"geometry":{"coordinates":[[[102.632858,-3.5107590000000015],[102.625713,-3.511090000000001],[102.625142,-3.515787],[102.632956,-3.515446000000001],[102.632858,-3.5107590000000015]]],"geodesic":true,"type":"Polygon"},"id":"20120328033516","properties":{"AOT":0.074,"H2O":4.6399993896484375,"O3":0.255,"date":{"type":"Date","value":1332905716000},"doy":88.14949074074075,"solar_z":25.81125,"swir":false,"tir":{"bkgd_rad":{"tir1":null,"tir2":null,"tir3":null,"tir4":null,"tir5":null},"lake_rad":{"tir1":null,"tir2":null,"tir3":null,"tir4":null,"tir5":null}},"vnir":{"mean_radiance":{"green":null,"nir":null,"red":null},"pixel_counts":{"cloud":1916.0,"lake":0.0,"valid":{"green":1916,"nir":1916,"red":1916}}}},"type":"Feature"},{"geometry":{"coordinates":[[[102.632858,-3.5107590000000015],[102.625713,-3.511090000000001],[102.625142,-3.515787],[102.632956,-3.515446000000001],[102.632858,-3.5107590000000015]]],"geodesic":true,"type":"Polygon"},"id":"20120522034122","properties":{"AOT":0.149,"H2O":4.919999694824218,"O3":0.248,"date":{"type":"Date","value":1337658082000},"doy":143.15372685185184,"solar_z":31.886541,"swir":false,"tir":{"bkgd_rad":{"tir1":6.721456714285718,"tir2":7.37115142857143,"tir3":7.862026904761902,"tir4":8.025774523809524,"tir5":7.6309880952380915},"lake_rad":{"tir1":null,"tir2":null,"tir3":null,"tir4":null,"tir5":null}},"vnir":{"mean_radiance":{"green":null,"nir":null,"red":null},"pixel_counts":{"cloud":1914.0,"lake":0.0,"valid":{"green":1916,"nir":1916,"red":1916}}}},"type":"Feature"},{"geometry":{"coordinates":[[[102.632858,-3.5107590000000015],[102.625713,-3.511090000000001],[102.625142,-3.515787],[102.632956,-3.515446000000001],[102.632858,-3.5107590000000015]]],"geodesic":true,"type":"Polygon"},"id":"20121022033504","properties":{"AOT":0.137,"H2O":4.619999694824219,"O3":0.251,"date":{"type":"Date","value":1350876904000},"doy":296.14935185185186,"solar_z":20.907415999999998,"swir":false,"tir":{"bkgd_rad":{"tir1":7.911945692307691,"tir2":8.556732527472526,"tir3":9.037424615384614,"tir4":9.196009252747253,"tir5":8.762267582417586},"lake_rad":{"tir1":null,"tir2":null,"tir3":null,"tir4":null,"tir5":null}},"vnir":{"mean_radiance":{"green":null,"nir":null,"red":null},"pixel_counts":{"cloud":1916.0,"lake":2.0,"valid":{"green":1916,"nir":1916,"red":1916}}}},"type":"Feature"},{"geometry":{"coordinates":[[[102.632858,-3.5107590000000015],[102.625713,-3.511090000000001],[102.625142,-3.515787],[102.632956,-3.515446000000001],[102.632858,-3.5107590000000015]]],"geodesic":true,"type":"Polygon"},"id":"20130416033556","properties":{"AOT":0.058,"H2O":4.519999694824219,"O3":0.255,"date":{"type":"Date","value":1366083356000},"doy":106.1499537037037,"solar_z":27.267668,"swir":false,"tir":{"bkgd_rad":{"tir1":null,"tir2":null,"tir3":null,"tir4":null,"tir5":null},"lake_rad":{"tir1":null,"tir2":null,"tir3":null,"tir4":null,"tir5":null}},"vnir":{"mean_radiance":{"green":null,"nir":null,"red":null},"pixel_counts":{"cloud":1916.0,"lake":0.0,"valid":{"green":1916,"nir":1916,"red":1916}}}},"type":"Feature"},{"geometry":{"coordinates":[[[102.632858,-3.5107590000000015],[102.625713,-3.511090000000001],[102.625142,-3.515787],[102.632956,-3.515446000000001],[102.632858,-3.5107590000000015]]],"geodesic":true,"type":"Polygon"},"id":"20130610034147","properties":{"AOT":0.101,"H2O":5.189999389648437,"O3":0.255,"date":{"type":"Date","value":1370835707000},"doy":161.1540162037037,"solar_z":33.80184,"swir":false,"tir":{"bkgd_rad":{"tir1":7.485851172413799,"tir2":8.179906344827584,"tir3":8.702208620689653,"tir4":8.819438551724138,"tir5":8.398665},"lake_rad":{"tir1":null,"tir2":null,"tir3":null,"tir4":null,"tir5":null}},"vnir":{"mean_radiance":{"green":111.202,"nir":47.58239999999999,"red":66.05640000000001},"pixel_counts":{"cloud":553.0,"lake":10.0,"valid":{"green":1916,"nir":1916,"red":1916}}}},"type":"Feature"},{"geometry":{"coordinates":[[[102.632858,-3.5107590000000015],[102.625713,-3.511090000000001],[102.625142,-3.515787],[102.632956,-3.515446000000001],[102.632858,-3.5107590000000015]]],"geodesic":true,"type":"Polygon"},"id":"20130806033540","properties":{"AOT":0.07,"H2O":5.019999694824219,"O3":0.266,"date":{"type":"Date","value":1375760140000},"doy":218.14976851851853,"solar_z":32.154226,"swir":false,"tir":{"bkgd_rad":{"tir1":null,"tir2":null,"tir3":null,"tir4":null,"tir5":null},"lake_rad":{"tir1":null,"tir2":null,"tir3":null,"tir4":null,"tir5":null}},"vnir":{"mean_radiance":{"green":null,"nir":null,"red":null},"pixel_counts":{"cloud":1916.0,"lake":0.0,"valid":{"green":1916,"nir":1916,"red":1916}}}},"type":"Feature"},{"geometry":{"coordinates":[[[102.632858,-3.5107590000000015],[102.625713,-3.511090000000001],[102.625142,-3.515787],[102.632956,-3.515446000000001],[102.632858,-3.5107590000000015]]],"geodesic":true,"type":"Polygon"},"id":"20130930034135","properties":{"AOT":0.216,"H2O":4.289999389648438,"O3":0.264,"date":{"type":"Date","value":1380512495000},"doy":273.1538773148148,"solar_z":19.427295,"swir":false,"tir":{"bkgd_rad":{"tir1":null,"tir2":null,"tir3":null,"tir4":null,"tir5":null},"lake_rad":{"tir1":null,"tir2":null,"tir3":null,"tir4":null,"tir5":null}},"vnir":{"mean_radiance":{"green":null,"nir":null,"red":null},"pixel_counts":{"cloud":1916.0,"lake":0.0,"valid":{"green":1916,"nir":1916,"red":1916}}}},"type":"Feature"},{"geometry":{"coordinates":[[[102.632858,-3.5107590000000015],[102.625713,-3.511090000000001],[102.625142,-3.515787],[102.632956,-3.515446000000001],[102.632858,-3.5107590000000015]]],"geodesic":true,"type":"Polygon"},"id":"20140318033529","properties":{"AOT":0.051,"H2O":4.969999694824219,"O3":0.263,"date":{"type":"Date","value":1395113729000},"doy":77.14964120370371,"solar_z":25.817049999999995,"swir":false,"tir":{"bkgd_rad":{"tir1":7.3636668,"tir2":8.012604,"tir3":8.522627333333334,"tir4":8.712946733333334,"tir5":8.356516666666666},"lake_rad":{"tir1":null,"tir2":null,"tir3":null,"tir4":null,"tir5":null}},"vnir":{"mean_radiance":{"green":null,"nir":null,"red":null},"pixel_counts":{"cloud":1916.0,"lake":1.0,"valid":{"green":1916,"nir":1916,"red":1916}}}},"type":"Feature"},{"geometry":{"coordinates":[[[102.632858,-3.5107590000000015],[102.625713,-3.511090000000001],[102.625142,-3.515787],[102.632956,-3.515446000000001],[102.632858,-3.5107590000000015]]],"geodesic":true,"type":"Polygon"},"id":"20140512034202","properties":{"AOT":0.08,"H2O":4.719999694824219,"O3":0.258,"date":{"type":"Date","value":1399866122000},"doy":132.15418981481483,"solar_z":30.032612,"swir":false,"tir":{"bkgd_rad":{"tir1":null,"tir2":null,"tir3":null,"tir4":null,"tir5":null},"lake_rad":{"tir1":null,"tir2":null,"tir3":null,"tir4":null,"tir5":null}},"vnir":{"mean_radiance":{"green":null,"nir":null,"red":null},"pixel_counts":{"cloud":1916.0,"lake":0.0,"valid":{"green":1916,"nir":1916,"red":1916}}}},"type":"Feature"},{"geometry":{"coordinates":[[[102.632858,-3.5107590000000015],[102.625713,-3.511090000000001],[102.625142,-3.515787],[102.632956,-3.515446000000001],[102.632858,-3.5107590000000015]]],"geodesic":true,"type":"Polygon"},"id":"20141129033543","properties":{"AOT":0.075,"H2O":5.55,"O3":0.238,"date":{"type":"Date","value":1417232143000},"doy":333.14980324074077,"solar_z":26.711726,"swir":false,"tir":{"bkgd_rad":{"tir1":null,"tir2":null,"tir3":null,"tir4":null,"tir5":null},"lake_rad":{"tir1":null,"tir2":null,"tir3":null,"tir4":null,"tir5":null}},"vnir":{"mean_radiance":{"green":null,"nir":null,"red":null},"pixel_counts":{"cloud":1916.0,"lake":0.0,"valid":{"green":1916,"nir":1916,"red":1916}}}},"type":"Feature"},{"geometry":{"coordinates":[[[102.632858,-3.5107590000000015],[102.625713,-3.511090000000001],[102.625142,-3.515787],[102.632956,-3.515446000000001],[102.632858,-3.5107590000000015]]],"geodesic":true,"type":"Polygon"},"id":"20150727033645","properties":{"AOT":0.253,"H2O":4.159999847412109,"O3":0.268,"date":{"type":"Date","value":1437968205000},"doy":208.15052083333333,"solar_z":33.630917,"swir":false,"tir":{"bkgd_rad":{"tir1":7.544031677419352,"tir2":8.17711741935484,"tir3":8.604839354838711,"tir4":8.930388725806448,"tir5":8.520963709677417},"lake_rad":{"tir1":null,"tir2":null,"tir3":null,"tir4":null,"tir5":null}},"vnir":{"mean_radiance":{"green":null,"nir":null,"red":null},"pixel_counts":{"cloud":1893.0,"lake":4.0,"valid":{"green":1916,"nir":1916,"red":1916}}}},"type":"Feature"}]}